stimbposd/__init__.py
stimbposd/bp_osd.py
stimbposd/config.py
stimbposd/dem_to_matrices.py
stimbposd/sinter_bp_osd.py
stimbposd-0.1.0.dist-info/METADATA
stimbposd-0.1.0.dist-info/WHEEL
stimbposd-0.1.0.dist-info/licenses/LICENSE
stimbposd-0.1.0.dist-info/RECORD
