Metadata-Version: 2.4
Name: stimbposd
Version: 0.1.0
Summary: Decode stim circuits with belief propagation and ordered statistics decoding (BP+OSD)
Project-URL: Homepage, https://github.com/oscarhiggott/stimbposd
Project-URL: Issues, https://github.com/oscarhiggott/stimbposd/issues
Author: Oscar Higgott
License-File: LICENSE
Classifier: License :: OSI Approved :: MIT License
Classifier: Operating System :: OS Independent
Classifier: Programming Language :: Python :: 3
Requires-Python: >=3.7
Requires-Dist: ldpc
Requires-Dist: numpy<=2.2.6
Requires-Dist: sinter>=1.12.0
Requires-Dist: stim
Provides-Extra: dev
Requires-Dist: pytest; extra == 'dev'
Requires-Dist: ruff; extra == 'dev'
